__init__.py
admm_fit.py
config.py
cvae.py
cvaeglrm.py
diagnosis_plots.py
hyper_parameter_optimization.py
imputation.py
local_fit_numba.py
model_fit.py
parse_opt.py
preprocess.py
run_model.py
utils.py
version.py
sdeper-1.7.1.dist-info/METADATA
sdeper-1.7.1.dist-info/WHEEL
sdeper-1.7.1.dist-info/entry_points.txt
sdeper-1.7.1.dist-info/top_level.txt
sdeper-1.7.1.dist-info/RECORD
