Metadata-Version: 2.4
Name: sdeper
Version: 1.7.1
Summary: Spatial Deconvolution method with Platform Effect Removal
Home-page: https://az7jh2.github.io/SDePER/
Author: Ningshan Li
Author-email: hill103.2@gmail.com
Project-URL: Documentation, https://sdeper.readthedocs.io/en/latest/
Project-URL: Source, https://github.com/az7jh2/SDePER
Project-URL: Changelog, https://sdeper.readthedocs.io/en/latest/changelog.html
Classifier: Development Status :: 5 - Production/Stable
Classifier: License :: OSI Approved :: MIT License
Classifier: Programming Language :: Python :: 3.9
Classifier: Programming Language :: Python :: 3.10
Classifier: Operating System :: POSIX :: Linux
Requires-Python: >=3.9, <3.11
Requires-Dist: numpy==1.26.4
Requires-Dist: scipy==1.11.4
Requires-Dist: pandas==1.4.3
Requires-Dist: matplotlib==3.5.2
Requires-Dist: scikit-learn==1.1.1
Requires-Dist: numba==0.59.1
Requires-Dist: openpyxl==3.0.10
Requires-Dist: tensorflow-cpu==2.15.0
Requires-Dist: scanpy==1.9.1
Requires-Dist: scikit-misc==0.1.4
Requires-Dist: seaborn==0.13.2
Requires-Dist: umap-learn==0.5.3
Requires-Dist: distinctipy==1.2.2
Requires-Dist: reportlab==4.1.0
Requires-Dist: opencv-python-headless==4.9.0.80
Dynamic: author
Dynamic: author-email
Dynamic: classifier
Dynamic: description
Dynamic: description-content-type
Dynamic: home-page
Dynamic: project-url
Dynamic: requires-dist
Dynamic: requires-python
Dynamic: summary
